spdx3merge/__init__.py
spdx3merge/__main__.py
spdx3merge/main.py
spdx3merge/spdx3.py
spdx3merge/version.py
spdx3merge-0.0.3.dist-info/METADATA
spdx3merge-0.0.3.dist-info/WHEEL
spdx3merge-0.0.3.dist-info/entry_points.txt
spdx3merge-0.0.3.dist-info/licenses/LICENSE
spdx3merge-0.0.3.dist-info/RECORD
