Metadata-Version: 2.3
Name: spdx3merge
Version: 0.0.3
Summary: Merge SPDX 3 data files
Project-URL: Homepage, https://github.com/JPEWdev/spdx3merge
Project-URL: Repository, https://github.com/JPEWdev/spdx3merge.git
Project-URL: Issues, https://github.com/JPEWdev/spdx3merge/issues
Author-email: Joshua Watt <JPEWhacker@gmail.com>
Classifier: Development Status :: 4 - Beta
Classifier: Intended Audience :: Developers
Classifier: License :: OSI Approved :: MIT License
Classifier: Programming Language :: Python :: 3
Classifier: Programming Language :: Python :: 3.9
Classifier: Programming Language :: Python :: 3.10
Classifier: Programming Language :: Python :: 3.11
Classifier: Programming Language :: Python :: 3.12
Classifier: Topic :: Software Development :: Build Tools
Requires-Python: >=3.9
Provides-Extra: dev
Requires-Dist: flake8>=7.0.0; extra == 'dev'
Requires-Dist: pytest-cov>=4.1; extra == 'dev'
Requires-Dist: pytest-server-fixtures>=1.7; extra == 'dev'
Requires-Dist: pytest>=7.4; extra == 'dev'
Requires-Dist: shacl2code==0.0.15; extra == 'dev'
